music22/__init__.py
music22/audio.py
music22/core.py
music22/diastema.py
music22/modalis.py
music22/scale.py
music22/stats.py
music22/test_scale.py
music22-0.0.8.dist-info/LICENSE
music22-0.0.8.dist-info/METADATA
music22-0.0.8.dist-info/WHEEL
music22-0.0.8.dist-info/top_level.txt
music22-0.0.8.dist-info/RECORD
