Metadata-Version: 2.1
Name: music22
Version: 0.0.8
Summary: A tool for musicological analysis from audio files. Now it is focused on modal music analysis : Scale analysis, tonic detection
Home-page: https://gitlab.com/AnasGhrab/music22
Author: Anas Ghrab
Author-email: anas.ghrab@gmail.com
License: GNU
Keywords: musicology analysis from non-symbolic data
Platform: UNKNOWN
Classifier: License :: OSI Approved :: GNU General Public License v3 (GPLv3)
Classifier: Programming Language :: Python :: 3
Classifier: Topic :: Multimedia :: Sound/Audio :: Analysis
Requires-Python: >=3.6
License-File: LICENSE
Requires-Dist: numpy
Requires-Dist: matplotlib
Requires-Dist: scipy
Requires-Dist: pandas
Requires-Dist: essentia
Requires-Dist: librosa
